pid4cat_model/__init__.py
pid4cat_model/_version.py
pid4cat_model/handle_api.py
pid4cat_model/iso7064.py
pid4cat_model/datamodel/__init__.py
pid4cat_model/datamodel/pid4cat_model.py
pid4cat_model/datamodel/pid4cat_model_pydantic.py
pid4cat_model/schema/README.md
pid4cat_model/schema/media_types.yaml
pid4cat_model/schema/pid4cat_model.yaml
pid4cat_model-0.4.2.dist-info/METADATA
pid4cat_model-0.4.2.dist-info/WHEEL
pid4cat_model-0.4.2.dist-info/licenses/LICENSE
pid4cat_model-0.4.2.dist-info/RECORD
