Metadata-Version: 2.4
Name: pid4cat-model
Version: 0.4.2
Summary: Python model equivalent of LinkML datamodel for handle-based PIDs for resources in catalysis (pid4cat)
Author-email: David Linke <david.linke@catalysis.de>
Maintainer-email: David Linke <david.linke@catalysis.de>
License-Expression: MIT
License-File: LICENSE
Requires-Python: <4.0,>=3.11
Requires-Dist: click<8.2.0,>=8.1.7
Requires-Dist: httpx<0.29.0,>=0.28.1
Requires-Dist: linkml-runtime>=1.9.2
